rstatmon/__init__.py
rstatmon/application.py
rstatmon/auth.py
rstatmon/database.py
rstatmon/db_setup.py
rstatmon/general.py
rstatmon/mylogger.py
rstatmon/passhash.py
rstatmon/random_int.py
rstatmon/routes.py
rstatmon/rstat.py
rstatmon/session_manager.py
rstatmon/statdata.py
rstatmon/usermodel.py
rstatmon/config/settings/general.json
rstatmon/config/settings/settings.json
rstatmon/config/settings/settings.json.org
rstatmon/config/user_model/model_prop.json
rstatmon/config/user_model/user_model.json
rstatmon/static/js/home_graph.js
rstatmon/static/settings/settings.json
rstatmon/templates/add_pyfile.html
rstatmon/templates/calendar.html
rstatmon/templates/delete.html
rstatmon/templates/home.html
rstatmon/templates/layout.html
rstatmon/templates/layout.html.bak
rstatmon/templates/login.html
rstatmon/templates/login_template.html
rstatmon/templates/logout.html
rstatmon/templates/profile.html
rstatmon/templates/register.html
rstatmon/templates/result.html
rstatmon/templates/setting_theme.html
rstatmon/templates/settings.html
rstatmon/templates/user_model.html
rstatmon/templates/user_model.html.org
rstatmon/templates/jinja/body.html
rstatmon-1.2.1.data/data/src/rstatmon/config/settings/general.json
rstatmon-1.2.1.data/data/src/rstatmon/config/settings/settings.json
rstatmon-1.2.1.data/data/src/rstatmon/config/settings/settings.json.org
rstatmon-1.2.1.data/data/src/rstatmon/config/user_model/model_prop.json
rstatmon-1.2.1.data/data/src/rstatmon/config/user_model/user_model.json
rstatmon-1.2.1.data/data/src/rstatmon/static/js/home_graph.js
rstatmon-1.2.1.data/data/src/rstatmon/static/settings/settings.json
rstatmon-1.2.1.data/data/src/rstatmon/templates/add_pyfile.html
rstatmon-1.2.1.data/data/src/rstatmon/templates/calendar.html
rstatmon-1.2.1.data/data/src/rstatmon/templates/delete.html
rstatmon-1.2.1.data/data/src/rstatmon/templates/home.html
rstatmon-1.2.1.data/data/src/rstatmon/templates/layout.html
rstatmon-1.2.1.data/data/src/rstatmon/templates/layout.html.bak
rstatmon-1.2.1.dist-info/LICENSE
rstatmon-1.2.1.dist-info/METADATA
rstatmon-1.2.1.dist-info/WHEEL
rstatmon-1.2.1.dist-info/entry_points.txt
rstatmon-1.2.1.dist-info/top_level.txt
rstatmon-1.2.1.dist-info/RECORD
